innate/__init__.py
innate/cli.py
innate/core.py
innate/manipulation.py
innate_sdk-0.1.0.dist-info/METADATA
innate_sdk-0.1.0.dist-info/WHEEL
innate_sdk-0.1.0.dist-info/entry_points.txt
innate_sdk-0.1.0.dist-info/RECORD
