Metadata-Version: 2.4
Name: innate-sdk
Version: 0.1.0
Summary: SDK for Innate robots
Author-email: Axel Peytavin <axel@innate.bot>, Vignesh Anand <vignesh@innate.bot>
Requires-Python: >=3.7
Requires-Dist: click>=8.0
Requires-Dist: typer>=0.9.0
